PyCockByEmir/__init__.py
PyCockByEmir/formula.py
PyCockByEmir-0.1.0.dist-info/LICENSE
PyCockByEmir-0.1.0.dist-info/METADATA
PyCockByEmir-0.1.0.dist-info/WHEEL
PyCockByEmir-0.1.0.dist-info/top_level.txt
PyCockByEmir-0.1.0.dist-info/RECORD
